uniquorn.py
Uniquorn-0.0.1.dist-info/LICENSE
Uniquorn-0.0.1.dist-info/METADATA
Uniquorn-0.0.1.dist-info/WHEEL
Uniquorn-0.0.1.dist-info/top_level.txt
Uniquorn-0.0.1.dist-info/RECORD
