Metadata-Version: 2.1
Name: Uniquorn
Version: 0.0.1
Summary: Create class instances with the same parameters only once
Author-email: Eric Nieuwland <eric.nieuwland+uniquorn@gmail.com>
Project-URL: Homepage, https://github.com/eric-nieuwland/uniquorn
Project-URL: Bug Tracker, https://github.com/eric-nieuwland/uniquorn/issues
Classifier: Programming Language :: Python :: 3
Classifier: License :: OSI Approved :: MIT License
Classifier: Operating System :: OS Independent
Requires-Python: >=3.11
License-File: LICENSE
